{"ヤマトホマレ":{"name":"ヤマトホマレ","career_stats":{"total_races":5,"wins":0,"top3":0,"win_rate":0.0,"top3_rate":0.0},"running_style":"追込","running_style_basis":{"sample_runs":5,"average_corner_position_rate":0.7599,"method":"近走最大10走の最終コーナー位置率から判定"},"distance_stats":{"1700":{"runs":3,"wins":0,"top3":0,"win_rate":0.0,"top3_rate":0.0},"1800":{"runs":2,"wins":0,"top3":0,"win_rate":0.0,"top3_rate":0.0}},"venue_stats":{"中山":{"runs":2,"wins":0,"top3":0,"win_rate":0.0,"top3_rate":0.0},"函館":{"runs":2,"wins":0,"top3":0,"win_rate":0.0,"top3_rate":0.0},"福島":{"runs":1,"wins":0,"top3":0,"win_rate":0.0,"top3_rate":0.0}},"track_condition_stats":{"良":{"runs":3,"wins":0,"top3":0,"win_rate":0.0,"top3_rate":0.0},"稍":{"runs":2,"wins":0,"top3":0,"win_rate":0.0,"top3_rate":0.0}},"surface_stats":{"ダート":{"runs":5,"wins":0,"top3":0,"win_rate":0.0,"top3_rate":0.0}},"closing_3f_stats":{"sample_runs":5,"avg_final_3f":40.22,"best_final_3f":38.5,"avg_final_3f_vs_race_avg":0.054,"avg_final_3f_rank":8.0},"enhanced_recent_runs":[{"date":"2024-06-23","raw_date":240623,"meeting":"1函6","venue":"函館","race_number":6,"race_id":"240623_1函6_6","race_name":"未勝利","field_size":11,"horse_number":10,"sex":"牝","age":3,"jockey":"大野拓弥","carried_weight":55.0,"surface":"ダート","distance":1700,"track_condition":"良","finish":7,"finish_raw":"７","time":"1:48.4","time_seconds":108.4,"margin":1.8,"corner_position":"11-10-8","corner_2":11,"corner_3":10,"corner_4":8,"final_3f":39.7,"horse_weight":456,"horse_weight_diff":4,"race_relative":{"finish_rate":0.6364,"final_corner_position_rate":0.7273,"final_3f_vs_race_avg":-0.6,"final_3f_rank":2,"time_vs_race_avg":0.54}},{"date":"2024-06-08","raw_date":240608,"meeting":"1函1","venue":"函館","race_number":6,"race_id":"240608_1函1_6","race_name":"未勝利","field_size":14,"horse_number":10,"sex":"牝","age":3,"jockey":"大野拓弥","carried_weight":55.0,"surface":"ダート","distance":1700,"track_condition":"良","finish":8,"finish_raw":"８","time":"1:48.8","time_seconds":108.8,"margin":2.8,"corner_position":"13-13-13","corner_2":13,"corner_3":13,"corner_4":13,"final_3f":38.5,"horse_weight":452,"horse_weight_diff":2,"race_relative":{"finish_rate":0.5714,"final_corner_position_rate":0.9286,"final_3f_vs_race_avg":-0.264,"final_3f_rank":6,"time_vs_race_avg":0.557}},{"date":"2024-03-31","raw_date":240331,"meeting":"3中4","venue":"中山","race_number":3,"race_id":"240331_3中4_3","race_name":"未勝利","field_size":14,"horse_number":13,"sex":"牝","age":3,"jockey":"五十嵐雄","carried_weight":55.0,"surface":"ダート","distance":1800,"track_condition":"稍","finish":12,"finish_raw":"12","time":"1:57.6","time_seconds":117.6,"margin":2.8,"corner_position":"10-10-10","corner_2":10,"corner_3":10,"corner_4":10,"final_3f":40.1,"horse_weight":450,"horse_weight_diff":0,"race_relative":{"finish_rate":0.8571,"final_corner_position_rate":0.7143,"final_3f_vs_race_avg":0.529,"final_3f_rank":13,"time_vs_race_avg":0.779}},{"date":"2024-03-10","raw_date":240310,"meeting":"2中6","venue":"中山","race_number":1,"race_id":"240310_2中6_1","race_name":"未勝利・牝","field_size":16,"horse_number":16,"sex":"牝","age":3,"jockey":"五十嵐雄","carried_weight":55.0,"surface":"ダート","distance":1800,"track_condition":"稍","finish":10,"finish_raw":"10","time":"1:59.4","time_seconds":119.4,"margin":3.2,"corner_position":"8-8-9","corner_2":8,"corner_3":8,"corner_4":9,"final_3f":42.7,"horse_weight":450,"horse_weight_diff":-6,"race_relative":{"finish_rate":0.625,"final_corner_position_rate":0.5625,"final_3f_vs_race_avg":0.544,"final_3f_rank":11,"time_vs_race_avg":0.375}},{"date":"2023-11-05","raw_date":231105,"meeting":"3福2","venue":"福島","race_number":6,"race_id":"231105_3福2_6","race_name":"新馬","field_size":15,"horse_number":5,"sex":"牝","age":2,"jockey":"五十嵐雄","carried_weight":55.0,"surface":"ダート","distance":1700,"track_condition":"良","finish":11,"finish_raw":"11","time":"1:52.4","time_seconds":112.4,"margin":5.0,"corner_position":"12-13-13","corner_2":12,"corner_3":13,"corner_4":13,"final_3f":40.1,"horse_weight":456,"race_relative":{"finish_rate":0.7333,"final_corner_position_rate":0.8667,"final_3f_vs_race_avg":0.06,"final_3f_rank":8,"time_vs_race_avg":0.767}}],"all_runs_count":5,"data_source":"JRA-VAN TARGET CSV export","prediction_policy":"odds_popularity_excluded"},"ヤマトホープシップ":{"name":"ヤマトホープシップ","career_stats":{"total_races":4,"wins":0,"top3":0,"win_rate":0.0,"top3_rate":0.0},"running_style":"差し","running_style_basis":{"sample_runs":4,"average_corner_position_rate":0.3884,"method":"近走最大10走の最終コーナー位置率から判定"},"distance_stats":{"1700":{"runs":2,"wins":0,"top3":0,"win_rate":0.0,"top3_rate":0.0},"1600":{"runs":1,"wins":0,"top3":0,"win_rate":0.0,"top3_rate":0.0},"1800":{"runs":1,"wins":0,"top3":0,"win_rate":0.0,"top3_rate":0.0}},"venue_stats":{"札幌":{"runs":2,"wins":0,"top3":0,"win_rate":0.0,"top3_rate":0.0},"中山":{"runs":1,"wins":0,"top3":0,"win_rate":0.0,"top3_rate":0.0},"東京":{"runs":1,"wins":0,"top3":0,"win_rate":0.0,"top3_rate":0.0}},"track_condition_stats":{"良":{"runs":4,"wins":0,"top3":0,"win_rate":0.0,"top3_rate":0.0}},"surface_stats":{"ダート":{"runs":4,"wins":0,"top3":0,"win_rate":0.0,"top3_rate":0.0}},"closing_3f_stats":{"sample_runs":4,"avg_final_3f":39.3,"best_final_3f":37.6,"avg_final_3f_vs_race_avg":-0.55,"avg_final_3f_rank":6.0},"enhanced_recent_runs":[{"date":"2020-09-05","raw_date":200905,"meeting":"2札7","venue":"札幌","race_number":3,"race_id":"200905_2札7_3","race_name":"未勝利","field_size":14,"horse_number":8,"sex":"牝","age":3,"jockey":"大野拓弥","carried_weight":54.0,"surface":"ダート","distance":1700,"track_condition":"良","finish":6,"finish_raw":"６","time":"1:47.7","time_seconds":107.7,"margin":1.9,"corner_position":"3-2-4","corner_2":3,"corner_3":2,"corner_4":4,"final_3f":38.8,"horse_weight":464,"horse_weight_diff":2,"race_relative":{"finish_rate":0.4286,"final_corner_position_rate":0.2857,"final_3f_vs_race_avg":0.336,"final_3f_rank":8,"time_vs_race_avg":-0.229}},{"date":"2020-08-22","raw_date":200822,"meeting":"2札3","venue":"札幌","race_number":3,"race_id":"200822_2札3_3","race_name":"未勝利・牝","field_size":14,"horse_number":12,"sex":"牝","age":3,"jockey":"大野拓弥","carried_weight":54.0,"surface":"ダート","distance":1700,"track_condition":"良","finish":5,"finish_raw":"５","time":"1:47.9","time_seconds":107.9,"margin":1.3,"corner_position":"2-1-2","corner_2":2,"corner_3":1,"corner_4":2,"final_3f":39.6,"horse_weight":462,"horse_weight_diff":4,"race_relative":{"finish_rate":0.3571,"final_corner_position_rate":0.1429,"final_3f_vs_race_avg":0.043,"final_3f_rank":7,"time_vs_race_avg":-0.514}},{"date":"2020-02-02","raw_date":200202,"meeting":"1東2","venue":"東京","race_number":3,"race_id":"200202_1東2_3","race_name":"未勝利・牝","field_size":16,"horse_number":4,"sex":"牝","age":3,"jockey":"石橋脩","carried_weight":54.0,"surface":"ダート","distance":1600,"track_condition":"良","finish":5,"finish_raw":"５","time":"1:40.2","time_seconds":100.2,"margin":1.4,"corner_position":"15-15","corner_3":15,"corner_4":15,"final_3f":37.6,"horse_weight":460,"horse_weight_diff":2,"race_relative":{"finish_rate":0.3125,"final_corner_position_rate":0.9375,"final_3f_vs_race_avg":-1.819,"final_3f_rank":1,"time_vs_race_avg":-0.444}},{"date":"2020-01-06","raw_date":200106,"meeting":"1中2","venue":"中山","race_number":6,"race_id":"200106_1中2_6","race_name":"新馬・牝","field_size":16,"horse_number":13,"sex":"牝","age":3,"jockey":"勝浦正樹","carried_weight":54.0,"surface":"ダート","distance":1800,"track_condition":"良","finish":5,"finish_raw":"５","time":"1:59.0","time_seconds":119.0,"margin":1.0,"corner_position":"3-3-3","corner_2":3,"corner_3":3,"corner_4":3,"final_3f":41.2,"horse_weight":458,"race_relative":{"finish_rate":0.3125,"final_corner_position_rate":0.1875,"final_3f_vs_race_avg":-0.762,"final_3f_rank":8,"time_vs_race_avg":-1.838}}],"all_runs_count":4,"data_source":"JRA-VAN TARGET CSV export","prediction_policy":"odds_popularity_excluded"}}